data/__init__.py
data/historical.py
data/live.py
orders/__init__.py
orders/kite.py
orders/orders.py
pysysstra-0.1.0.dist-info/METADATA
pysysstra-0.1.0.dist-info/WHEEL
pysysstra-0.1.0.dist-info/top_level.txt
pysysstra-0.1.0.dist-info/RECORD
