Metadata-Version: 2.1
Name: pysysstra
Version: 0.1.0
Summary: Official Python Library for Sysstra Algo Trading
Home-page: https://github.com/sysstra/pysysstra
Author: Anurag Singh Kushwah
Author-email: anurag786kushwah@gmail.com
Classifier: Programming Language :: Python :: 3
Classifier: License :: OSI Approved :: MIT License
Classifier: Operating System :: OS Independent
Requires-Python: >=3.6
Requires-Dist: requests
Requires-Dist: numpy
Requires-Dist: pandas-ta
Requires-Dist: redis
Requires-Dist: json
Requires-Dist: datetime
Requires-Dist: itertools
Requires-Dist: traceback
